dessca/__init__.py
dessca/dessca.py
dessca-1.0.0.dist-info/METADATA
dessca-1.0.0.dist-info/WHEEL
dessca-1.0.0.dist-info/licenses/LICENSE
dessca-1.0.0.dist-info/RECORD
