Metadata-Version: 2.4
Name: dessca
Version: 1.0.0
Summary: Improved Exploring Starts by Kernel Density Estimation-Based State-Space Coverage Acceleration in Reinforcement Learning.
Project-URL: Homepage, https://github.com/max-schenke/DESSCA
Project-URL: Issues, https://github.com/max-schenke/DESSCA/issues
Author: Maximilian Schenke
License-File: LICENSE
Classifier: License :: OSI Approved :: MIT License
Classifier: Operating System :: OS Independent
Classifier: Programming Language :: Python :: 3
Requires-Python: >=3.11
Requires-Dist: kalepy>=1.4.3
Requires-Dist: numpy>=2.3.5
Requires-Dist: pyswarms>=1.3.0
